{
  "schema_version": "policy-definitions/v1",
  "policy_set_id": "negative-unknown-rule-policy-set",
  "policy_set_version": "0.0.0-negative",
  "supported_rule_types": ["production_allowed_false"],
  "outcome_precedence": ["deny", "escalate", "approval_required", "allow"],
  "policies": [
    {
      "policy_id": "unknown-rule",
      "version": "0.0.0-negative",
      "lifecycle_status": "active",
      "decision": "deny",
      "rule_type": "unknown_rule_type",
      "message": "Unknown rules must fail closed."
    }
  ],
  "runtime_integration_authorized": false,
  "production_decision_execution_authorized": false
}
